test_rest_api/__init__.py
test_rest_api/__main__.py
test_rest_api/assertion/__init__.py
test_rest_api/assertion/assertion.py
test_rest_api/bug/__init__.py
test_rest_api/bug/bug.py
test_rest_api/cli/__init__.py
test_rest_api/cli/cli.py
test_rest_api/constant/__init__.py
test_rest_api/constant/constant.py
test_rest_api/decorator/__init__.py
test_rest_api/decorator/decorator.py
test_rest_api/decorator/hashtag_filter.py
test_rest_api/environment/__init__.py
test_rest_api/environment/environment.py
test_rest_api/exceptions/__init__.py
test_rest_api/exceptions/assertion_exception.py
test_rest_api/exceptions/base_exception.py
test_rest_api/exceptions/bug_creation_exception.py
test_rest_api/exceptions/constant_exception.py
test_rest_api/exceptions/decorators.py
test_rest_api/exceptions/environment_exception.py
test_rest_api/exceptions/rest_api_creation_exception.py
test_rest_api/exceptions/rest_api_send_exception.py
test_rest_api/exceptions/testdata_exception.py
test_rest_api/exceptions/variable_exception.py
test_rest_api/loggers/__init__.py
test_rest_api/loggers/test_rest_api_console_logger.py
test_rest_api/loggers/test_rest_api_report_logger.py
test_rest_api/logging/__init__.py
test_rest_api/logging/config.py
test_rest_api/logging/filters.py
test_rest_api/logging/formatters.py
test_rest_api/logging/handlers.py
test_rest_api/logging/setup.py
test_rest_api/reporting/__init__.py
test_rest_api/reporting/html.py
test_rest_api/reporting/html1.py
test_rest_api/reporting/html_backup_20_04_2025.py
test_rest_api/reporting/html_working_backup_before_tailwind.py
test_rest_api/reporting/report.py
test_rest_api/rest_api/__init__.py
test_rest_api/rest_api/method.py
test_rest_api/rest_api/response.py
test_rest_api/rest_api/rest_api.py
test_rest_api/runner/__init__.py
test_rest_api/runner/runner.py
test_rest_api/runtime/__init__.py
test_rest_api/runtime/runtime.py
test_rest_api/settings/__init__.py
test_rest_api/settings/command_line_execution.py
test_rest_api/settings/logging.py
test_rest_api-0.0.0.0.57.dist-info/licenses/LICENSE
test_rest_api-0.0.0.0.57.dist-info/METADATA
test_rest_api-0.0.0.0.57.dist-info/WHEEL
test_rest_api-0.0.0.0.57.dist-info/entry_points.txt
test_rest_api-0.0.0.0.57.dist-info/top_level.txt
test_rest_api-0.0.0.0.57.dist-info/RECORD
