Metadata-Version: 2.4
Name: test_rest_api
Version: 0.0.0.0.57
Summary: Asynchronous Test Framework #HighPerformance #EasyToLearn #FastToCode #AsyncTests
Home-page: https://github.com/troymjose/test_rest_api
Author: Troy M Jose
Author-email: 
Project-URL: Source, https://github.com/troymjose/test_rest_api
Project-URL: Tracker, https://github.com/troymjose/test_rest_api/issues
Keywords: test,unittest,restapi,testframework,asyncio,async,asynchronous,testingframework,rest,api,python,python3,testing,unittesting,automation,automationtest,automationtesting,restapitest,restapitesting,restapiunittest,restapiunittesting,restapiautomation,restapiautomationtest,restapiautomationtesting,apitest,apitesting,apiunittest,apiunittesting,apiautomation,apiautomationtest,apiautomationtesting
Classifier: Programming Language :: Python :: 3.12
Classifier: Programming Language :: Python :: 3.13
Classifier: License :: OSI Approved :: MIT License
Classifier: Operating System :: OS Independent
Classifier: Framework :: AsyncIO
Classifier: Framework :: aiohttp
Classifier: Topic :: Utilities
Classifier: Topic :: Software Development
Classifier: Topic :: Software Development :: Testing
Classifier: Topic :: Software Development :: Testing :: Unit
Classifier: Topic :: Software Development :: Quality Assurance
Classifier: Topic :: Software Development :: Libraries
Classifier: Topic :: Software Development :: Libraries :: Python Modules
Classifier: Topic :: Software Development :: Libraries :: Application Frameworks
License-File: LICENSE
Requires-Dist: aiohttp
Requires-Dist: Jinja2
Requires-Dist: python-dotenv
Dynamic: author
Dynamic: classifier
Dynamic: description
Dynamic: description-content-type
Dynamic: home-page
Dynamic: keywords
Dynamic: license-file
Dynamic: project-url
Dynamic: requires-dist
Dynamic: summary
